CHANGES.txt
COPYRIGHT.txt
LICENSE.txt
README.txt
base.cfg
setup.py
tl/__init__.py
tl/cmd.py
tl/readline.py
tl.cli.egg-info/PKG-INFO
tl.cli.egg-info/SOURCES.txt
tl.cli.egg-info/dependency_links.txt
tl.cli.egg-info/namespace_packages.txt
tl.cli.egg-info/not-zip-safe
tl.cli.egg-info/requires.txt
tl.cli.egg-info/top_level.txt
tl/cli/__init__.py
tl/cli/_cmd.py
tl/cli/_readline.py
tl/cli/edit.py
tl/cli/edit.txt
tl/cli/page.py
tl/cli/page.txt
tl/cli/readline.txt
tl/cli/tests.py