Metadata-Version: 1.0
Name: tl.cli
Version: 0.2
Summary: Various command line interface utilities.
